fepops/__init__.py
fepops/__main__.py
fepops/fepops.py
fepops/fepops_persistent/__init__.py
fepops/fepops_persistent/fepops_persistent_abc.py
fepops/fepops_persistent/fepopsdb_json.py
fepops/fepops_persistent/fepopsdb_sqlite.py
fepops/fepops_persistent/utils.py
fepops/utils/__init__.py
fepops/utils/dude_preprocessor.py
fepops/utils/mol_filter.py
fepops-1.8.3.dist-info/LICENSE.md
fepops-1.8.3.dist-info/METADATA
fepops-1.8.3.dist-info/WHEEL
fepops-1.8.3.dist-info/entry_points.txt
fepops-1.8.3.dist-info/top_level.txt
fepops-1.8.3.dist-info/RECORD
