Metadata-Version: 2.1
Name: fepops
Version: 1.8.3
Summary: OpenFEPOPS; A Python implementation of the FEPOPS molecular similarity method
Author: Yan-Kai Chen, Steven Shave
Project-URL: Homepage, https://github.com/JustinYKC/FEPOPS
Keywords: molecular similarity,ligand based virtual screening
Requires-Python: >=3.9
License-File: LICENSE.md
Requires-Dist: rdkit <2023.9.1,>=2022.9.2
Requires-Dist: numpy >=1.22.4
Requires-Dist: pandas >=1.5.0
Requires-Dist: scikit-learn >=1.3.0
Requires-Dist: scipy >=1.7.0
Requires-Dist: torch
Requires-Dist: fast-pytorch-kmeans >=0.1.9
Requires-Dist: fire >=0.5.0
Requires-Dist: tqdm >=4.48.0
Provides-Extra: dev
Requires-Dist: black ==23.3.0 ; extra == 'dev'
Requires-Dist: pytest ==7.4.0 ; extra == 'dev'
Requires-Dist: build ==0.10.0 ; extra == 'dev'
